{
  "form": {
    "VendorName": "Unspecified",
    "VendorID": "0x000",
    "ProductCode": "0x00ab123",
    "ProfileNo": "5001",
    "RevisionNumber": "0x001",
    "SerialNumber": "0x001",
    "HWversion": "0.0.1",
    "SWversion": "0.0.1",
    "EEPROMsize": "2048",
    "RxMailboxOffset": "0x1000",
    "TxMailboxOffset": "0x1200",
    "MailboxSize": "512",
    "SM2Offset": "0x1600",
    "SM3Offset": "0x1A00",
    "TextGroupType": "DigIn",
    "TextGroupName5": "Digital input/output",
    "ImageName": "IMGCBY",
    "TextDeviceType": "IODemoApp",
    "TextDeviceName": "LAN9252 SPI demo",
    "Port0Physical": "Y",
    "Port1Physical": "Y",
    "Port2Physical": " ",
    "Port3Physical": " ",
    "ESC": "LAN9252",
    "SPImode": "0",
    "CoeDetailsEnableSDO": "EnableSDO",
    "CoeDetailsEnableSDOInfo": "EnableSDOInfo",
    "CoeDetailsEnablePDOAssign": "EnablePDOAssign",
    "CoeDetailsEnablePDOConfiguration": "EnablePDOConfiguration",
    "CoeDetailsEnableUploadAtStartup": "EnableUploadAtStartup",
    "CoeDetailsEnableSDOCompleteAccess": "EnableSDOCompleteAccess"
  },
  "od": {
    "sdo": {},
    "txpdo": {
      "6000": {
        "otype": "RECORD",
        "name": "can1_rx_head",
        "access": "RO",
        "items": [
          {
            "name": "Max SubIndex"
          },
          {
            "name": "StdId",
            "dtype": "UNSIGNED32",
            "data": "&Obj.can1_rx_head.StdId",
            "value": "0",
            "access": "WO"
          },
          {
            "name": "ExtId",
            "dtype": "UNSIGNED32",
            "data": "&Obj.can1_rx_head.ExtId",
            "value": "0",
            "access": "WO"
          },
          {
            "name": "IDE",
            "dtype": "UNSIGNED8",
            "value": "0",
            "access": "WO",
            "data": "&Obj.can1_rx_head.IDE"
          },
          {
            "name": "RTR",
            "dtype": "UNSIGNED8",
            "value": "0",
            "access": "RO",
            "data": "&Obj.can1_rx_head.RTR"
          },
          {
            "name": "DLC",
            "dtype": "UNSIGNED8",
            "value": "0",
            "access": "RO",
            "data": "&Obj.can1_rx_head.DLC"
          }
        ],
        "pdo_mappings": [
          "txpdo"
        ]
      },
      "6001": {
        "otype": "ARRAY",
        "name": "can1_rx_data",
        "access": "RO",
        "items": [
          {
            "name": "Max SubIndex"
          },
          {
            "name": "0",
            "data": "&Obj.can1_rx_data[0]",
            "value": "0"
          },
          {
            "name": "1",
            "value": "0",
            "data": "&Obj.can1_rx_data[1]"
          },
          {
            "name": "2",
            "data": "&Obj.can1_rx_data[2]",
            "value": "0"
          },
          {
            "name": "3",
            "value": "0",
            "data": "&Obj.can1_rx_data[3]"
          },
          {
            "name": "4",
            "value": "0",
            "data": "&Obj.can1_rx_data[4]"
          },
          {
            "name": "5",
            "value": "0",
            "data": "&Obj.can1_rx_data[5]"
          },
          {
            "name": "6",
            "value": "0",
            "data": "&Obj.can1_rx_data[6]"
          },
          {
            "name": "7",
            "value": "0",
            "data": "&Obj.can1_rx_data[7]"
          }
        ],
        "pdo_mappings": [
          "txpdo"
        ],
        "dtype": "UNSIGNED8"
      }
    },
    "rxpdo": {
      "7000": {
        "otype": "VAR",
        "name": "Led",
        "access": "RO",
        "pdo_mappings": [
          "rxpdo"
        ],
        "dtype": "INTEGER8",
        "value": "0",
        "data": "&Obj.Led"
      },
      "7001": {
        "otype": "RECORD",
        "name": "can1_tx_head",
        "access": "RO",
        "items": [
          {
            "name": "Max SubIndex"
          },
          {
            "name": "StdId",
            "dtype": "UNSIGNED32",
            "data": "&Obj.can1_tx_head.StdId",
            "value": "0",
            "access": "RO"
          },
          {
            "name": "ExtId",
            "dtype": "UNSIGNED32",
            "value": "0",
            "access": "RO",
            "data": "&Obj.can1_tx_head.ExtId"
          },
          {
            "name": "IDE",
            "dtype": "UNSIGNED8",
            "value": "0",
            "access": "RO",
            "data": "&Obj.can1_tx_head.IDE"
          },
          {
            "name": "RTR",
            "dtype": "UNSIGNED8",
            "value": "0",
            "access": "RO",
            "data": "&Obj.can1_tx_head.RTR"
          },
          {
            "name": "DLC",
            "dtype": "UNSIGNED8",
            "value": "0",
            "access": "RO",
            "data": "&Obj.can1_tx_head.DLC"
          }
        ],
        "pdo_mappings": [
          "rxpdo"
        ]
      },
      "7002": {
        "otype": "ARRAY",
        "name": "can1_tx_data",
        "access": "RO",
        "items": [
          {
            "name": "Max SubIndex"
          },
          {
            "name": "0",
            "data": "&Obj.can1_tx_data[0]",
            "value": "0"
          },
          {
            "name": "1",
            "value": "0",
            "data": "&Obj.can1_tx_data[1]"
          },
          {
            "name": "2",
            "value": "0",
            "data": "&Obj.can1_tx_data[2]"
          },
          {
            "name": "3",
            "value": "0",
            "data": "&Obj.can1_tx_data[3]"
          },
          {
            "name": "4",
            "value": "0",
            "data": "&Obj.can1_tx_data[4]"
          },
          {
            "name": "5",
            "value": "0",
            "data": "&Obj.can1_tx_data[5]"
          },
          {
            "name": "6",
            "value": "0",
            "data": "&Obj.can1_tx_data[6]"
          },
          {
            "name": "7",
            "value": "0",
            "data": "&Obj.can1_tx_data[7]"
          }
        ],
        "pdo_mappings": [
          "rxpdo"
        ],
        "dtype": "UNSIGNED8"
      }
    }
  },
  "dc": []
}